openobd_protocol/__init__.py
openobd_protocol/Communication/CommunicationServices_pb2.py
openobd_protocol/Communication/CommunicationServices_pb2.pyi
openobd_protocol/Communication/CommunicationServices_pb2_grpc.py
openobd_protocol/Communication/Messages/Doip_pb2.py
openobd_protocol/Communication/Messages/Doip_pb2.pyi
openobd_protocol/Communication/Messages/Isotp_pb2.py
openobd_protocol/Communication/Messages/Isotp_pb2.pyi
openobd_protocol/Communication/Messages/Kline_pb2.py
openobd_protocol/Communication/Messages/Kline_pb2.pyi
openobd_protocol/Communication/Messages/Raw_pb2.py
openobd_protocol/Communication/Messages/Raw_pb2.pyi
openobd_protocol/Communication/Messages/Terminal15_pb2.py
openobd_protocol/Communication/Messages/Terminal15_pb2.pyi
openobd_protocol/Communication/Messages/Tp20_pb2.py
openobd_protocol/Communication/Messages/Tp20_pb2.pyi
openobd_protocol/Configuration/ConfigurationServices_pb2.py
openobd_protocol/Configuration/ConfigurationServices_pb2.pyi
openobd_protocol/Configuration/ConfigurationServices_pb2_grpc.py
openobd_protocol/Configuration/Messages/BusConfiguration_pb2.py
openobd_protocol/Configuration/Messages/BusConfiguration_pb2.pyi
openobd_protocol/Configuration/Messages/CanBus_pb2.py
openobd_protocol/Configuration/Messages/CanBus_pb2.pyi
openobd_protocol/Configuration/Messages/Configuration_pb2.py
openobd_protocol/Configuration/Messages/Configuration_pb2.pyi
openobd_protocol/Configuration/Messages/DoipBus_pb2.py
openobd_protocol/Configuration/Messages/DoipBus_pb2.pyi
openobd_protocol/Configuration/Messages/KlineBus_pb2.py
openobd_protocol/Configuration/Messages/KlineBus_pb2.pyi
openobd_protocol/Configuration/Messages/Terminal15Bus_pb2.py
openobd_protocol/Configuration/Messages/Terminal15Bus_pb2.pyi
openobd_protocol/ConnectionMonitor/ConnectionMonitorServices_pb2.py
openobd_protocol/ConnectionMonitor/ConnectionMonitorServices_pb2.pyi
openobd_protocol/ConnectionMonitor/ConnectionMonitorServices_pb2_grpc.py
openobd_protocol-1.25.3.dist-info/licenses/LICENSE
openobd_protocol-1.25.3.dist-info/METADATA
openobd_protocol-1.25.3.dist-info/WHEEL
openobd_protocol-1.25.3.dist-info/top_level.txt
openobd_protocol-1.25.3.dist-info/RECORD
