Metadata-Version: 2.4
Name: openobd-protocol
Version: 1.25.3
Summary: Jifeline Networks openOBD Protocol Buffers gRPC
Author-email: Gerhard de Koning Gans <gerhard@factorit.nl>, Wessel van Tunen <wessel@factorit.nl>, Rohaan Ghosh <rohaan@factorit.nl>, Sander de Mooij <sanderdemooij@factorit.nl>
Maintainer-email: Gerhard de Koning Gans <gerhard@factorit.nl>, Wessel van Tunen <wessel@factorit.nl>, Rohaan Ghosh <rohaan@factorit.nl>, Sander de Mooij <sanderdemooij@factorit.nl>
License: Copyright (c) 2024 Jifeline Networks B.V.
Project-URL: Homepage, https://www.openobd.com
Keywords: OpenOBD,Protocol,gRPC,Jifeline,Remote,Diagnostics,OBD,On-board,Automotive,Car,Vehicle,CAN,K-line,DoIP
Platform: any
Classifier: Development Status :: 4 - Beta
Classifier: License :: OSI Approved :: MIT License
Classifier: Operating System :: OS Independent
Classifier: Programming Language :: Python :: 3
Classifier: Topic :: Communications
Requires-Python: >=3.8
License-File: LICENSE
Requires-Dist: grpcio-tools==1.60.1
Requires-Dist: grpcio==1.60.1
Requires-Dist: protobuf>=4.25.2
Dynamic: license-file
